ngcli/__init__.py
ngcli/format.py
ngcli/neug_cli.py
ngcli-0.1.1.dist-info/METADATA
ngcli-0.1.1.dist-info/WHEEL
ngcli-0.1.1.dist-info/entry_points.txt
ngcli-0.1.1.dist-info/top_level.txt
ngcli-0.1.1.dist-info/RECORD
