Metadata-Version: 2.4
Name: ngcli
Version: 0.1.1
Summary: GraphScope CLI shell for NeuG
Author-email: GraphScope Team <graphscope@alibaba-inc.com>
License-Expression: Apache-2.0
Keywords: Graph,Embedded,Graph Database,Command Line Interface,CLI
Requires-Python: >=3.8
Requires-Dist: click>=8.0.0
Requires-Dist: tabulate>=0.9.0
Requires-Dist: PyYAML>=6.0.2
Requires-Dist: neug==0.1.0
Provides-Extra: test
Requires-Dist: pytest>=6.2.5; extra == "test"
Requires-Dist: black>=23.3.0; extra == "test"
Requires-Dist: flake8==4.0.1; extra == "test"
Requires-Dist: isort==5.10.1; extra == "test"
